midigpt/__init__.py
midigpt/components.py
midigpt/config.py
midigpt/gpt.py
midigpt/trainer.py
midigpt/utils.py
midigpt/datasets/__init__.py
midigpt/datasets/text_character.py
midigpt-0.0.1b5.dist-info/LICENSE
midigpt-0.0.1b5.dist-info/METADATA
midigpt-0.0.1b5.dist-info/WHEEL
midigpt-0.0.1b5.dist-info/top_level.txt
midigpt-0.0.1b5.dist-info/RECORD
