Metadata-Version: 2.1
Name: midigpt
Version: 0.0.1b5
Summary: midiGPT: A MIDI Music Generation Library
Home-page: https://github.com/johnnygreco/midiGPT
Classifier: Intended Audience :: Science/Research
Classifier: Programming Language :: Python :: 3
Classifier: Programming Language :: Python :: 3.8
Classifier: Programming Language :: Python :: 3.9
Classifier: Programming Language :: Python :: 3.10
Classifier: License :: OSI Approved :: MIT License
Classifier: Topic :: Scientific/Engineering
Classifier: Topic :: Scientific/Engineering :: Artificial Intelligence
Requires-Python: >=3.8
License-File: LICENSE
Requires-Dist: pydantic (==1.10.5)
Requires-Dist: rich (==13.3.2)
Requires-Dist: torch (==1.13.1)
Requires-Dist: tqdm (==4.65.0)
